data_analysis_toolbox/__init__.py
data_analysis_toolbox/data_analysis_toolbox.py
data_analysis_toolbox-0.0.2.dist-info/LICENSE
data_analysis_toolbox-0.0.2.dist-info/METADATA
data_analysis_toolbox-0.0.2.dist-info/WHEEL
data_analysis_toolbox-0.0.2.dist-info/top_level.txt
data_analysis_toolbox-0.0.2.dist-info/RECORD
