Metadata-Version: 2.1
Name: data-analysis-toolbox
Version: 0.0.2
Summary: A wrapper for commonly used data analysis routines
Author-email: Sam Wyss <sjwyss@outlook.com>
Project-URL: Homepage, https://github.com/samwyss/Data-Analysis-Toolbox
Project-URL: Bug Tracker, https://github.com/samwyss/Data-Analysis-Toolbox/issues
Classifier: Programming Language :: Python :: 3
Classifier: License :: OSI Approved :: MIT License
Classifier: Operating System :: OS Independent
Requires-Python: >=3.10.6
License-File: LICENSE
